{
    "model": "squeezenet1_0-1M",
    "function params": {},
    "train accuracy": 25.558,
    "test accuracy": 25.811,
    "accuracy difference": -0.2530000000000001,
    "num epochs": 100,
    "num layers": 9,
    "num params": 15178,
    "Conv2d-1": {
        "kernel size": [
            7,
            7
        ],
        "stride": [
            2,
            2
        ]
    },
    "ReLU-2": {},
    "MaxPool2d-3": {
        "kernel size": 3,
        "stride": 2
    },
    "MaxPool2d-4": {
        "kernel size": 3,
        "stride": 2
    },
    "Dropout-5": {},
    "Conv2d-6": {
        "kernel size": [
            1,
            1
        ],
        "stride": [
            1,
            1
        ]
    },
    "ReLU-7": {},
    "AdaptiveAvgPool2d-8": {},
    "SqueezeNet-9": {}
}