{
    "model": "custom_resnet1",
    "function params": {
        "block": "BasicBlock",
        "layers": [
            2,
            8,
            2,
            2
        ],
        "groups": 1,
        "width per group": 64
    },
    "train accuracy": 99.163,
    "test accuracy": 98.57,
    "accuracy difference": 0.5930000000000035,
    "num epochs": 3,
    "num layers": 111,
    "num params": 12947914,
    "layers": [
        {
            "name": "Conv2d-1",
            "kernel size": [
                7,
                7
            ],
            "stride": [
                2,
                2
            ]
        },
        {
            "name": "BatchNorm2d-2"
        },
        {
            "name": "ReLU-3"
        },
        {
            "name": "MaxPool2d-4",
            "kernel size": 3,
            "stride": 2
        },
        {
            "name": "Conv2d-5",
            "kernel size": [
                3,
                3
            ],
            "stride": [
                1,
                1
            ]
        },
        {
            "name": "BatchNorm2d-6"
        },
        {
            "name": "ReLU-7"
        },
        {
            "name": "Conv2d-8",
            "kernel size": [
                3,
                3
            ],
            "stride": [
                1,
                1
            ]
        },
        {
            "name": "BatchNorm2d-9"
        },
        {
            "name": "ReLU-10"
        },
        {
            "name": "BasicBlock-11",
            "stride": 1
        },
        {
            "name": "Conv2d-12",
            "kernel size": [
                3,
                3
            ],
            "stride": [
                1,
                1
            ]
        },
        {
            "name": "BatchNorm2d-13"
        },
        {
            "name": "ReLU-14"
        },
        {
            "name": "Conv2d-15",
            "kernel size": [
                3,
                3
            ],
            "stride": [
                1,
                1
            ]
        },
        {
            "name": "BatchNorm2d-16"
        },
        {
            "name": "ReLU-17"
        },
        {
            "name": "BasicBlock-18",
            "stride": 1
        },
        {
            "name": "Conv2d-19",
            "kernel size": [
                3,
                3
            ],
            "stride": [
                2,
                2
            ]
        },
        {
            "name": "BatchNorm2d-20"
        },
        {
            "name": "ReLU-21"
        },
        {
            "name": "Conv2d-22",
            "kernel size": [
                3,
                3
            ],
            "stride": [
                1,
                1
            ]
        },
        {
            "name": "BatchNorm2d-23"
        },
        {
            "name": "Conv2d-24",
            "kernel size": [
                1,
                1
            ],
            "stride": [
                2,
                2
            ]
        },
        {
            "name": "BatchNorm2d-25"
        },
        {
            "name": "ReLU-26"
        },
        {
            "name": "BasicBlock-27",
            "stride": 2
        },
        {
            "name": "Conv2d-28",
            "kernel size": [
                3,
                3
            ],
            "stride": [
                1,
                1
            ]
        },
        {
            "name": "BatchNorm2d-29"
        },
        {
            "name": "ReLU-30"
        },
        {
            "name": "Conv2d-31",
            "kernel size": [
                3,
                3
            ],
            "stride": [
                1,
                1
            ]
        },
        {
            "name": "BatchNorm2d-32"
        },
        {
            "name": "ReLU-33"
        },
        {
            "name": "BasicBlock-34",
            "stride": 1
        },
        {
            "name": "Conv2d-35",
            "kernel size": [
                3,
                3
            ],
            "stride": [
                1,
                1
            ]
        },
        {
            "name": "BatchNorm2d-36"
        },
        {
            "name": "ReLU-37"
        },
        {
            "name": "Conv2d-38",
            "kernel size": [
                3,
                3
            ],
            "stride": [
                1,
                1
            ]
        },
        {
            "name": "BatchNorm2d-39"
        },
        {
            "name": "ReLU-40"
        },
        {
            "name": "BasicBlock-41",
            "stride": 1
        },
        {
            "name": "Conv2d-42",
            "kernel size": [
                3,
                3
            ],
            "stride": [
                1,
                1
            ]
        },
        {
            "name": "BatchNorm2d-43"
        },
        {
            "name": "ReLU-44"
        },
        {
            "name": "Conv2d-45",
            "kernel size": [
                3,
                3
            ],
            "stride": [
                1,
                1
            ]
        },
        {
            "name": "BatchNorm2d-46"
        },
        {
            "name": "ReLU-47"
        },
        {
            "name": "BasicBlock-48",
            "stride": 1
        },
        {
            "name": "Conv2d-49",
            "kernel size": [
                3,
                3
            ],
            "stride": [
                1,
                1
            ]
        },
        {
            "name": "BatchNorm2d-50"
        },
        {
            "name": "ReLU-51"
        },
        {
            "name": "Conv2d-52",
            "kernel size": [
                3,
                3
            ],
            "stride": [
                1,
                1
            ]
        },
        {
            "name": "BatchNorm2d-53"
        },
        {
            "name": "ReLU-54"
        },
        {
            "name": "BasicBlock-55",
            "stride": 1
        },
        {
            "name": "Conv2d-56",
            "kernel size": [
                3,
                3
            ],
            "stride": [
                1,
                1
            ]
        },
        {
            "name": "BatchNorm2d-57"
        },
        {
            "name": "ReLU-58"
        },
        {
            "name": "Conv2d-59",
            "kernel size": [
                3,
                3
            ],
            "stride": [
                1,
                1
            ]
        },
        {
            "name": "BatchNorm2d-60"
        },
        {
            "name": "ReLU-61"
        },
        {
            "name": "BasicBlock-62",
            "stride": 1
        },
        {
            "name": "Conv2d-63",
            "kernel size": [
                3,
                3
            ],
            "stride": [
                1,
                1
            ]
        },
        {
            "name": "BatchNorm2d-64"
        },
        {
            "name": "ReLU-65"
        },
        {
            "name": "Conv2d-66",
            "kernel size": [
                3,
                3
            ],
            "stride": [
                1,
                1
            ]
        },
        {
            "name": "BatchNorm2d-67"
        },
        {
            "name": "ReLU-68"
        },
        {
            "name": "BasicBlock-69",
            "stride": 1
        },
        {
            "name": "Conv2d-70",
            "kernel size": [
                3,
                3
            ],
            "stride": [
                1,
                1
            ]
        },
        {
            "name": "BatchNorm2d-71"
        },
        {
            "name": "ReLU-72"
        },
        {
            "name": "Conv2d-73",
            "kernel size": [
                3,
                3
            ],
            "stride": [
                1,
                1
            ]
        },
        {
            "name": "BatchNorm2d-74"
        },
        {
            "name": "ReLU-75"
        },
        {
            "name": "BasicBlock-76",
            "stride": 1
        },
        {
            "name": "Conv2d-77",
            "kernel size": [
                3,
                3
            ],
            "stride": [
                2,
                2
            ]
        },
        {
            "name": "BatchNorm2d-78"
        },
        {
            "name": "ReLU-79"
        },
        {
            "name": "Conv2d-80",
            "kernel size": [
                3,
                3
            ],
            "stride": [
                1,
                1
            ]
        },
        {
            "name": "BatchNorm2d-81"
        },
        {
            "name": "Conv2d-82",
            "kernel size": [
                1,
                1
            ],
            "stride": [
                2,
                2
            ]
        },
        {
            "name": "BatchNorm2d-83"
        },
        {
            "name": "ReLU-84"
        },
        {
            "name": "BasicBlock-85",
            "stride": 2
        },
        {
            "name": "Conv2d-86",
            "kernel size": [
                3,
                3
            ],
            "stride": [
                1,
                1
            ]
        },
        {
            "name": "BatchNorm2d-87"
        },
        {
            "name": "ReLU-88"
        },
        {
            "name": "Conv2d-89",
            "kernel size": [
                3,
                3
            ],
            "stride": [
                1,
                1
            ]
        },
        {
            "name": "BatchNorm2d-90"
        },
        {
            "name": "ReLU-91"
        },
        {
            "name": "BasicBlock-92",
            "stride": 1
        },
        {
            "name": "Conv2d-93",
            "kernel size": [
                3,
                3
            ],
            "stride": [
                2,
                2
            ]
        },
        {
            "name": "BatchNorm2d-94"
        },
        {
            "name": "ReLU-95"
        },
        {
            "name": "Conv2d-96",
            "kernel size": [
                3,
                3
            ],
            "stride": [
                1,
                1
            ]
        },
        {
            "name": "BatchNorm2d-97"
        },
        {
            "name": "Conv2d-98",
            "kernel size": [
                1,
                1
            ],
            "stride": [
                2,
                2
            ]
        },
        {
            "name": "BatchNorm2d-99"
        },
        {
            "name": "ReLU-100"
        },
        {
            "name": "BasicBlock-101",
            "stride": 2
        },
        {
            "name": "Conv2d-102",
            "kernel size": [
                3,
                3
            ],
            "stride": [
                1,
                1
            ]
        },
        {
            "name": "BatchNorm2d-103"
        },
        {
            "name": "ReLU-104"
        },
        {
            "name": "Conv2d-105",
            "kernel size": [
                3,
                3
            ],
            "stride": [
                1,
                1
            ]
        },
        {
            "name": "BatchNorm2d-106"
        },
        {
            "name": "ReLU-107"
        },
        {
            "name": "BasicBlock-108",
            "stride": 1
        },
        {
            "name": "AdaptiveAvgPool2d-109"
        },
        {
            "name": "Linear-110"
        },
        {
            "name": "ResNet-111"
        }
    ]
}