{
    "model": "vgg11_bn-8",
    "function params": {
        "cfg": "A",
        "batch norm": true
    },
    "train accuracy": 11.237,
    "test accuracy": 11.35,
    "accuracy difference": -0.11299999999999955,
    "num epochs": 100,
    "num layers": 13,
    "num params": 17027082,
    "layers": [
        {
            "name": "MaxPool2d-1",
            "kernel size": 2,
            "stride": 2
        },
        {
            "name": "MaxPool2d-2",
            "kernel size": 2,
            "stride": 2
        },
        {
            "name": "MaxPool2d-3",
            "kernel size": 2,
            "stride": 2
        },
        {
            "name": "MaxPool2d-4",
            "kernel size": 2,
            "stride": 2
        },
        {
            "name": "AdaptiveAvgPool2d-5"
        },
        {
            "name": "Linear-6"
        },
        {
            "name": "ReLU-7"
        },
        {
            "name": "Dropout-8"
        },
        {
            "name": "Linear-9"
        },
        {
            "name": "ReLU-10"
        },
        {
            "name": "Dropout-11"
        },
        {
            "name": "Linear-12"
        },
        {
            "name": "VGG-13"
        }
    ]
}